savant/__init__.py
BaseballSavant-0.0.2.dist-info/LICENSE
BaseballSavant-0.0.2.dist-info/METADATA
BaseballSavant-0.0.2.dist-info/WHEEL
BaseballSavant-0.0.2.dist-info/top_level.txt
BaseballSavant-0.0.2.dist-info/RECORD
