Metadata-Version: 2.1
Name: BaseballSavant
Version: 0.0.2
Summary: API wrapper for the MLB Baseball Savant website
Home-page: https://github.com/JLpython-py/BaseballSavant.py
Author: Jacob Lee
Author-email: JLpython@outlook.com
License: UNKNOWN
Platform: UNKNOWN
Classifier: Development Status :: 1 - Planning
Classifier: Intended Audience :: Developers
Classifier: License :: OSI Approved :: MIT License
Classifier: Operating System :: OS Independent
Classifier: Programming Language :: Python :: 3
Classifier: Programming Language :: Python :: 3.8
Classifier: Programming Language :: Python :: 3.9
Classifier: Programming Language :: Python :: 3.10
Requires-Python: >=3.8
License-File: LICENSE
